picwriter/__init__.py
picwriter/geomeep.py
picwriter/mcm.py
picwriter/mcts.py
picwriter/meep_compute_transmission_spectra.py
picwriter/picsim.py
picwriter/test.py
picwriter/toolkit.py
picwriter/components/__init__.py
picwriter/components/adiabaticcoupler.py
picwriter/components/alignmentmarker.py
picwriter/components/bb_directionalcoupler.py
picwriter/components/bbend.py
picwriter/components/broadbanddc.py
picwriter/components/contradc.py
picwriter/components/dbr.py
picwriter/components/directionalcoupler.py
picwriter/components/disk.py
picwriter/components/ebend.py
picwriter/components/electrical.py
picwriter/components/fullcoupler.py
picwriter/components/gratingcoupler.py
picwriter/components/mmi1x2.py
picwriter/components/mmi2x2.py
picwriter/components/mzi.py
picwriter/components/ring.py
picwriter/components/sbend.py
picwriter/components/spiral.py
picwriter/components/spiral2.py
picwriter/components/spiral_old.py
picwriter/components/stripslotconverter.py
picwriter/components/stripslotcoupler.py
picwriter/components/stripslotmmiconverter.py
picwriter/components/stripslotmmicoupler.py
picwriter/components/stripslotyconverter.py
picwriter/components/stripslotycoupler.py
picwriter/components/swgcontradc.py
picwriter/components/taper.py
picwriter/components/waveguide (dkita-ThinkPad-P50's conflicted copy 2018-02-06).py
picwriter/components/waveguide.py
picwriter/components/ysplitter.py
picwriter/components/zerolengthcavity.py
picwriter-0.5.dist-info/LICENSE
picwriter-0.5.dist-info/METADATA
picwriter-0.5.dist-info/WHEEL
picwriter-0.5.dist-info/top_level.txt
picwriter-0.5.dist-info/RECORD
