Metadata-Version: 2.1
Name: picwriter
Version: 0.5
Summary: Mask generation tool
Home-page: http://github.com/DerekK88/picwriter
Author: Derek Kita
Author-email: UNKNOWN
License: MIT
Keywords: mask writing library
Platform: UNKNOWN
Classifier: Development Status :: 3 - Alpha
Classifier: Intended Audience :: Science/Research
Classifier: Topic :: Scientific/Engineering :: Electronic Design Automation (EDA)
Classifier: License :: OSI Approved :: MIT License
Classifier: Programming Language :: Python :: 2
Classifier: Programming Language :: Python :: 2.7
Classifier: Programming Language :: Python :: 3
Classifier: Programming Language :: Python :: 3.4
Classifier: Programming Language :: Python :: 3.5
Classifier: Programming Language :: Python :: 3.6
Requires-Dist: gdspy
Requires-Dist: numpy
